CHANGES.md
LICENSE
MANIFEST.in
README.md
numtraits.py
setup.py
test_numtraits.py
numtraits.egg-info/PKG-INFO
numtraits.egg-info/SOURCES.txt
numtraits.egg-info/dependency_links.txt
numtraits.egg-info/requires.txt
numtraits.egg-info/top_level.txt