Metadata-Version: 1.0
Name: numtraits
Version: 0.2
Summary: Numerical traits for Python objects
Home-page: https://github.com/astrofrog/numtraits
Author: Thomas Robitaille
Author-email: thomas.robitaille@gmail.com
License: BSD
Platform: UNKNOWN
